{
  "video_id": "Ted1IrlzkiY",
  "title": "Imperialism the Highest Stage of Capitalism-CH 8: Decay of Capitalism",
  "description": "If you enjoyed our video please consider checking our website out : https://www.midwesternmarx.com/\n\nAlso, if you are interested in helping us fund our project become a Patron : https://www.patreon.com/MidwesternMarx\n\nCheck out our online library for FREE books on Socialism, Philosophy, History, and more:\nhttps://www.midwesternmarx.com/online...\n\nFollow us on Instagram: @midwesternmarx\nFollow us on Twitter: @MarxMidwest\nLike us on Facebook: @Midwestern Marx",
  "channel_id": "UC4j1g1gUv6jgJH49nJwEGIw",
  "channel_title": "Midwestern Marx",
  "published_at": "2021-01-03T20:52:08Z",
  "tags": [],
  "category_id": "27",
  "duration": "PT20M57S",
  "view_count": 2408,
  "like_count": 216,
  "comment_count": 10,
  "privacy_status": "public",
  "made_for_kids": false,
  "channel_name": "midwesternmarx",
  "ad_status": "Yes"
}